.source Test1.java
.class public Test1
.super java/lang/Object

.method public <init>()V
    .limit stack 1
    .limit locals 1
    aload_0
    invokespecial java/lang/Object/<init>()V
    return
.end method

.method public static bar()V
    .limit stack 0
    .limit locals 0
    return
.end method

.method public static foo(I)V
    .limit stack 1
    .limit locals 1
    iload_0
    ifne label0
    return
label0:
    invokestatic Test1/bar()V
    return
.end method

.method public static main([Ljava/lang/String;)V
    .limit stack 2
    .limit locals 1
    aload_0
    iconst_0
    aaload
    invokevirtual java/lang/String/length()I
    istore_0
    getstatic java/lang/System/out Ljava/io/PrintStream;
    ldc "Hello\n"
    invokevirtual java/io/PrintStream/println(Ljava/lang/String;)V
    iload_0
    iconst_4
    if_icmple label0
    iload_0
    iconst_5
    if_icmple label1
    invokestatic Test1/bar()V
    goto label0
label1:
    iload_0
    invokestatic Test1/foo(I)V
label0:
    getstatic java/lang/System/out Ljava/io/PrintStream;
    iload_0
    invokevirtual java/io/PrintStream/println(I)V
    return
.end method

