.source Test13.java
.class public Test13
.super java/lang/Object

.inner_class_attr 
.inner_class_spec_attr "Test13$2" "null" "null" static .end .inner_class_spec_attr
.inner_class_spec_attr "Test13$1" "null" "null" static .end .inner_class_spec_attr
.end .inner_class_attr

.field public static "x" I


.method public <init>()V
    .limit stack 1
    .limit locals 1
    aload_0
    invokespecial java/lang/Object/<init>()V
    return
.end method

.method public static main([Ljava/lang/String;)V
.throws java.lang.InterruptedException
    .limit stack 3
    .limit locals 2
    new Test13$1
    astore_0
    aload_0
    invokespecial Test13$1/<init>()V
    new Test13$2
    astore_1
    aload_1
    invokespecial Test13$2/<init>()V
    aload_0
    invokevirtual java/lang/Thread/start()V
    aload_1
    invokevirtual java/lang/Thread/start()V
    aload_0
    invokevirtual java/lang/Thread/join()V
    aload_1
    invokevirtual java/lang/Thread/join()V
    getstatic java/lang/System/out Ljava/io/PrintStream;
    new java/lang/StringBuilder
    dup
    invokespecial java/lang/StringBuilder/<init>()V
    ldc "x = "
    invokevirtual java/lang/StringBuilder/append(Ljava/lang/String;)Ljava/lang/StringBuilder;
    getstatic Test13/x I
    invokevirtual java/lang/StringBuilder/append(I)Ljava/lang/StringBuilder;
    invokevirtual java/lang/StringBuilder/toString()Ljava/lang/String;
    invokevirtual java/io/PrintStream/println(Ljava/lang/String;)V
    return
.end method

.method static <clinit>()V
    .limit stack 1
    .limit locals 0
    iconst_0
    putstatic Test13/x I
    return
.end method

