.source Test16.java
.class public Test16
.super java/lang/Object

.method public <init>()V
    .limit stack 1
    .limit locals 1
    aload_0
    invokespecial java/lang/Object/<init>()V
    return
.end method

.method public static main([Ljava/lang/String;)V
    .limit stack 4
    .limit locals 3
    new Overload
    astore_0
    aload_0
    invokespecial Overload/<init>()V
    aload_0
    bipush 10
    invokevirtual Overload/demo(I)V
    aload_0
    bipush 10
    bipush 20
    invokevirtual Overload/demo(II)V
    aload_0
    ldc2_w 5.5
    invokevirtual Overload/demo(D)D
    dstore_1
    getstatic java/lang/System/out Ljava/io/PrintStream;
    new java/lang/StringBuilder
    dup
    invokespecial java/lang/StringBuilder/<init>()V
    ldc "O/P : "
    invokevirtual java/lang/StringBuilder/append(Ljava/lang/String;)Ljava/lang/StringBuilder;
    dload_1
    invokevirtual java/lang/StringBuilder/append(D)Ljava/lang/StringBuilder;
    invokevirtual java/lang/StringBuilder/toString()Ljava/lang/String;
    invokevirtual java/io/PrintStream/println(Ljava/lang/String;)V
    return
.end method

