.source Test4.java
.class public Test4
.super java/lang/Object

.method public <init>()V
    .limit stack 1
    .limit locals 1
    aload_0
    invokespecial java/lang/Object/<init>()V
    return
.end method

.method static tailRecursion(I)V
    .limit stack 3
    .limit locals 1
    iload_0
    ifne label0
    return
label0:
    getstatic java/lang/System/out Ljava/io/PrintStream;
    new java/lang/StringBuilder
    dup
    invokespecial java/lang/StringBuilder/<init>()V
    ldc "x = "
    invokevirtual java/lang/StringBuilder/append(Ljava/lang/String;)Ljava/lang/StringBuilder;
    iload_0
    invokevirtual java/lang/StringBuilder/append(I)Ljava/lang/StringBuilder;
    invokevirtual java/lang/StringBuilder/toString()Ljava/lang/String;
    invokevirtual java/io/PrintStream/println(Ljava/lang/String;)V
    iload_0
    iconst_1
    isub
    invokestatic Test4/tailRecursion(I)V
    return
.end method

.method public static main([Ljava/lang/String;)V
    .limit stack 1
    .limit locals 1
    bipush 10
    invokestatic Test4/tailRecursion(I)V
    return
.end method

