.source Test3.java
.class public Test3
.super java/lang/Object

.method public <init>()V
    .limit stack 1
    .limit locals 1
    aload_0
    invokespecial java/lang/Object/<init>()V
    return
.end method

.method public static main([Ljava/lang/String;)V
    .limit stack 2
    .limit locals 1
    aload_0
    iconst_0
    aaload
    invokevirtual java/lang/String/length()I
    istore_0
    iload_0
    iconst_2
    if_icmpne label0
    iload_0
    invokestatic java/lang/System/exit(I)V
    goto label1
label0:
    iload_0
    iconst_3
    if_icmpne label1
    iload_0
    invokestatic java/lang/System/exit(I)V
label1:
    getstatic java/lang/System/out Ljava/io/PrintStream;
    iload_0
    invokevirtual java/io/PrintStream/println(I)V
    return
.end method

