.source Test5.java
.class public Test5
.super java/lang/Object

.method public <init>()V
    .limit stack 1
    .limit locals 1
    aload_0
    invokespecial java/lang/Object/<init>()V
    return
.end method

.method static recursion(I)I
    .limit stack 3
    .limit locals 1
    iload_0
    ifne label0
    iconst_0
    ireturn
label0:
    iload_0
    iload_0
    imul
    iload_0
    iconst_1
    isub
    invokestatic Test5/recursion(I)I
    iadd
    ireturn
.end method

.method public static main([Ljava/lang/String;)V
    .limit stack 2
    .limit locals 1
    iconst_3
    invokestatic java/lang/Integer/valueOf(I)Ljava/lang/Integer;
    iconst_4
    invokestatic java/lang/Integer/valueOf(I)Ljava/lang/Integer;
    astore_0
    invokevirtual java/lang/Integer/intValue()I
    aload_0
    invokevirtual java/lang/Integer/intValue()I
    iadd
    invokestatic java/lang/Integer/valueOf(I)Ljava/lang/Integer;
    astore_0
    aload_0
    invokevirtual java/lang/Integer/intValue()I
    invokestatic Test5/recursion(I)I
    pop
    getstatic java/lang/System/out Ljava/io/PrintStream;
    aload_0
    invokevirtual java/io/PrintStream/println(Ljava/lang/Object;)V
    return
.end method

